certimaker/__init__.py
certimaker/certimaker.py
certimaker-0.0.2.dist-info/LICENSE
certimaker-0.0.2.dist-info/METADATA
certimaker-0.0.2.dist-info/WHEEL
certimaker-0.0.2.dist-info/top_level.txt
certimaker-0.0.2.dist-info/RECORD
