Metadata-Version: 2.1
Name: certimaker
Version: 0.0.2
Summary: A package used to make word certificate easily
Home-page: https://github.com/iwuch/certimaker
Author: Doctor Wu
Author-email: 277500223@qq.com
License: UNKNOWN
Platform: UNKNOWN
Classifier: Programming Language :: Python :: 3
Classifier: License :: OSI Approved :: MIT License
Classifier: Operating System :: OS Independent
Requires-Python: >=3.6
